LICENSE
MANIFEST.in
README.md
requirements-cairo.txt
requirements-dev.txt
requirements-examples.txt
requirements.txt
setup.py
py_staticmaps.egg-info/PKG-INFO
py_staticmaps.egg-info/SOURCES.txt
py_staticmaps.egg-info/dependency_links.txt
py_staticmaps.egg-info/entry_points.txt
py_staticmaps.egg-info/requires.txt
py_staticmaps.egg-info/top_level.txt
staticmaps/__init__.py
staticmaps/area.py
staticmaps/cairo_renderer.py
staticmaps/circle.py
staticmaps/cli.py
staticmaps/color.py
staticmaps/context.py
staticmaps/coordinates.py
staticmaps/image_marker.py
staticmaps/line.py
staticmaps/marker.py
staticmaps/meta.py
staticmaps/object.py
staticmaps/pillow_renderer.py
staticmaps/renderer.py
staticmaps/svg_renderer.py
staticmaps/tile_downloader.py
staticmaps/tile_provider.py
staticmaps/transformer.py