Metadata-Version: 2.1
Name: py-staticmaps
Version: 0.4.0
Summary: Create static map images (SVG, PNG) with markers, geodesic lines, ...
Home-page: https://github.com/flopp/py-staticmaps
Author: Florian Pigorsch
Author-email: mail@florian-pigorsch.de
License: UNKNOWN
Keywords: map staticmap osm markers
Platform: UNKNOWN
Classifier: Development Status :: 3 - Alpha
Classifier: Intended Audience :: Developers
Classifier: Topic :: Scientific/Engineering :: GIS
Classifier: License :: OSI Approved :: MIT License
Classifier: Programming Language :: Python :: 3
Classifier: Programming Language :: Python :: 3.6
Classifier: Programming Language :: Python :: 3.7
Classifier: Programming Language :: Python :: 3.8
Provides-Extra: cairo
Provides-Extra: dev
Provides-Extra: examples
